weblustrator/__init__.py
weblustrator/__main__.py
weblustrator/cli.py
weblustrator/page.py
weblustrator/render.py
weblustrator/sandbox.py
weblustrator/server.py
weblustrator/utils.py
weblustrator/views/index.html
weblustrator/views/index.tpl
weblustrator/views/mvp.css
weblustrator-0.1.5.dist-info/entry_points.txt
weblustrator-0.1.5.dist-info/WHEEL
weblustrator-0.1.5.dist-info/METADATA
weblustrator-0.1.5.dist-info/RECORD
