Metadata-Version: 2.1
Name: weblustrator
Version: 0.1.5
Summary: Generate illustrations using web technologies, such as svg, css, and javascript.
Author: RCJacH
Requires-Python: >=3.8,<4.0
Classifier: Programming Language :: Python :: 3
Classifier: Programming Language :: Python :: 3.10
Classifier: Programming Language :: Python :: 3.8
Classifier: Programming Language :: Python :: 3.9
Requires-Dist: Jinja2 (>=2.11.3,<3.0.0)
Requires-Dist: Pillow (>=8.1.0,<9.0.0)
Requires-Dist: PyYAML (>=5.4.1,<6.0.0)
Requires-Dist: bottle (>=0.12.19,<0.13.0)
Requires-Dist: click (>=7.1.2,<8.0.0)
Requires-Dist: livereload (>=2.6.3,<3.0.0)
Requires-Dist: nest-asyncio (>=1.5.1,<2.0.0)
Requires-Dist: pyppeteer (>=0.2.5,<0.3.0)
Requires-Dist: pypugjs (>=5.9.8,<6.0.0)
Requires-Dist: python-frontmatter (>=0.5.0,<0.6.0)
